apylaas/__init__.py
apylaas/transformers.py
apylaas/static/favicon.ico
apylaas/static/function.js
apylaas/static/index.js
apylaas/static/output.css
apylaas/templates/bad_module.html
apylaas/templates/base.html
apylaas/templates/form.html
apylaas/templates/index.html
apylaas/templates/method-404.html
apylaas-0.1.1.dist-info/METADATA
apylaas-0.1.1.dist-info/WHEEL
apylaas-0.1.1.dist-info/entry_points.txt
apylaas-0.1.1.dist-info/top_level.txt
apylaas-0.1.1.dist-info/RECORD
