Metadata-Version: 2.1
Name: apylaas
Version: 0.1.1
Summary: Any Python Library As A Service
License: MIT
Classifier: Development Status :: 4 - Beta
Classifier: Intended Audience :: Developers
Classifier: Programming Language :: Python :: 3.7
Requires-Python: >=3.7.*
